tomdanion_picsou/__init__.py
tomdanion_picsou/picsou.py
tomdanion_picsou-0.1.0.dist-info/METADATA
tomdanion_picsou-0.1.0.dist-info/WHEEL
tomdanion_picsou-0.1.0.dist-info/RECORD
